twinkly_client/__init__.py
twinkly_client/client.py
twinkly_client/const.py
twinkly_client-0.0.3.dist-info/LICENSE
twinkly_client-0.0.3.dist-info/METADATA
twinkly_client-0.0.3.dist-info/WHEEL
twinkly_client-0.0.3.dist-info/top_level.txt
twinkly_client-0.0.3.dist-info/RECORD
