Metadata-Version: 2.1
Name: twinkly-client
Version: 0.0.3
Summary: A package to communicate with Twinkly LED strings
Home-page: https://github.com/dr1rrb/py-twinkly-client
Author: dr1rrb
Author-email: py-twinkly-client@torick.net
License: UNKNOWN
Platform: UNKNOWN
Classifier: Programming Language :: Python :: 3
Classifier: License :: OSI Approved :: Apache Software License
Classifier: Operating System :: OS Independent
Classifier: Topic :: Home Automation
Requires-Python: >=3.6
License-File: LICENSE
Requires-Dist: aiohttp
